{"stats":{"minecraft:used":{"examplemod:freezing_carbon_block_upper":35,"minecraft:water_bucket":2,"minecraft:flint_and_steel":1,"examplemod:blazing_carbon_block_upper":97,"minecraft:stone_pickaxe":10,"minecraft:wooden_pickaxe":5,"minecraft:sandstone":2,"minecraft:stone":9,"minecraft:netherrack":87,"minecraft:torch":27,"minecraft:sand":8,"examplemod:blazing_carbon_block":57,"minecraft:tnt":6,"minecraft:crafting_table":10,"minecraft:blast_furnace":2,"minecraft:blue_ice":14,"examplemod:freezing_carbon_ore":32,"examplemod:blazing_carbon_block_lower":110,"minecraft:smoker":2,"minecraft:glass":14,"minecraft:stone_brick_slab":2,"minecraft:diamond_pickaxe":85,"examplemod:freezing_carbon_block_lower":15,"minecraft:grass_block":11,"minecraft:iron_pickaxe":14,"minecraft:lapis_ore":1,"examplemod:freezing_carbon_block":49,"minecraft:diamond_ore":3,"examplemod:blazing_carbon_ore":58,"minecraft:item_frame":10,"minecraft:coal_block":8,"minecraft:magma_block":10,"examplemod:big_slip":370,"minecraft:dark_oak_boat":5,"minecraft:furnace":12,"minecraft:ice":1,"minecraft:white_concrete":26,"minecraft:cooked_beef":1},"minecraft:custom":{"minecraft:interact_with_furnace":52,"minecraft:interact_with_crafting_table":15,"minecraft:play_one_minute":134088,"minecraft:leave_game":53,"minecraft:time_since_death":134088,"minecraft:time_since_rest":134088,"minecraft:sprint_one_cm":22858,"minecraft:damage_taken":60,"minecraft:walk_one_cm":203736,"minecraft:drop":17,"minecraft:fly_one_cm":332586,"minecraft:crouch_one_cm":9394,"minecraft:sneak_time":2651,"minecraft:walk_under_water_one_cm":62,"minecraft:boat_one_cm":9539,"minecraft:jump":450,"minecraft:interact_with_blast_furnace":24,"minecraft:walk_on_water_one_cm":410,"minecraft:interact_with_smoker":14,"minecraft:fall_one_cm":1561},"minecraft:dropped":{"examplemod:blazing_carbon_block_lower":3,"examplemod:blazing_carbon":4,"examplemod:freezing_carbon_ore":1,"examplemod:freezing_carbon":1,"minecraft:diamond_ore":1,"minecraft:coal":1,"examplemod:blazing_carbon_block_upper":3,"examplemod:big_slip":2,"minecraft:lapis_ore":1},"minecraft:mined":{"examplemod:freezing_carbon_ore":14,"examplemod:boom":1,"examplemod:blazing_carbon_block":2,"minecraft:glass":1,"minecraft:sandstone":2,"examplemod:big_slip":74,"examplemod:super_heated_carbon_ore":3,"examplemod:freezing_carbon_block":1,"minecraft:sand":11,"minecraft:netherrack":6,"examplemod:blazing_carbon_ore":20},"minecraft:crafted":{"minecraft:cooked_beef":66,"examplemod:freezing_carbon_block":2,"examplemod:blazing_carbon_block_lower":3,"examplemod:freezing_carbon_block_upper":2,"examplemod:blazing_carbon_block_upper":3,"minecraft:air":0,"minecraft:diamond":64,"examplemod:blazing_carbon_block":2,"examplemod:freezing_carbon_block_lower":1},"minecraft:picked_up":{"minecraft:lapis_ore":1,"examplemod:blazing_carbon_block_lower":3,"examplemod:freezing_carbon":14,"minecraft:dirt":52,"minecraft:apple":1,"examplemod:blazing_carbon_block_upper":3,"minecraft:diamond_ore":1,"minecraft:sandstone":104,"minecraft:cooked_porkchop":22,"examplemod:blazing_carbon":16,"examplemod:freezing_carbon_block":4,"minecraft:porkchop":42,"minecraft:sand":470,"examplemod:freezing_carbon_ore":1,"examplemod:blazing_carbon_block":67,"minecraft:oak_sapling":1,"examplemod:big_slip":28,"minecraft:netherrack":6,"minecraft:coal":1,"minecraft:cobblestone":17}},"DataVersion":2230}